[
  {
    "name": "賴建宏",
    "email": "ee12245@ntut.edu.tw",
    "latestUpdate": "2024-12-18 09:21:33",
    "objective": "1. 電晶體的結構與原理\n2.SPICE 的操作\n3. 放大器電路的原理與設計\n4. 如何操作模擬自己設計的晶片\n5.Layout 原理與 Laker 的基本操作",
    "schedule": "1. Structure and principle of transistor\n2.SPICE operation\n3. Principle and design of amplifier circuit\n4. How to operate the chip that simulates your own design\n5.Layout principle and basic operations of Laker",
    "scorePolicy": "Midterm 50%, Final 50%",
    "materials": "我自己寫的 PowerPoint 檔案",
    "consultation": "ext. 2237",
    "課程對應SDGs指標": "SDG8：尊嚴就業與經濟發展（Decent Work and Economic Growth）SDG9：產業創新與基礎設施（Industry, Innovation and Infrastructure）SDG17：夥伴關係（Partnerships for the Goals）",
    "remarks": "",
    "foreignLanguageTextbooks": false
  }
]
