[
  {
    "name": "蘇昱瑋",
    "email": "ywsu@mail.ntut.edu.tw",
    "latestUpdate": "2024-06-01 18:33:50",
    "objective": "本課程從物理的觀點談述分子材料。內容包括如下主題：1.\t力學 2.\t電學 3.\t光學 4.\t磁學 5.\t生物物理\nThis course introduces molecular materials from physics point of view.It will cover the following topics：1. Mechanics 2. Electronics3. Photonics4. Magnetics5. Biophysics",
    "schedule": "week 1~4: 力學\nweek 5~8: 電學 \nweek 9: 期中考\nweek 10~13:  光學\nweek 14~17: 磁學、生物物理\nweek 18: 期末考",
    "scorePolicy": "期中考、期末考",
    "materials": "Physics",
    "consultation": "課程 line 群組，與 office hour",
    "remarks": "",
    "foreignLanguageTextbooks": true
  }
]
