[
  {
    "name": "王麗蘭",
    "email": "leelan.wong@gmail.com",
    "latestUpdate": "2024-09-10 11:08:35",
    "objective": "課程藉由傳授馬來西亞語言以協助學生拓展東南亞的就業版圖，旨在培養學生的馬來西亞語基本溝通能力，運用馬來語與當地母語者打招呼、了解馬來文化、建立人際關係、購物、敘述事物等，以此來協助學生前往馬來西亞就業，作為兩國的經濟橋樑。\nIn order to embrace economic development of globalization, especially in Asian and Southeast Asian countries, there is a need to introduce and equip our students not only with the basic local language but also to understand the local culture so as to strengthen the economic tie between Taiwan and the Asian countries and to enhance the employment opportunities of our students in these Asian countries. This course aims to help students to understand and develop basic communication skills by utilizing Bahasa Malaysia (Malaysian language) to communicate with Malaysian in terms of greeting, business contact establishment, interpersonal communication, etc. Historical and geographical backgrounds of Malaysia and their local cultures will also be introduced.",
    "schedule": "第一週\t9/10\t課程介紹、馬來西亞風情與文化\t\n第二週\t9/17\t中秋節放假\t\n第三週\t9/24\t馬來語的發音一\t確定分組 16-18 組\n第四週\t10/01\t馬來語的發音二\t\n第五週\t10/08\t問候、基本稱呼\t\n第六週\t10/15\t你叫什麼名字\t美食體驗報告 1（2 組）\n第七週\t10/22\t你住在 / 來自哪裡\t美食體驗報告 2（2 組）\n第八週\t10/29\t數字 1,2,3\t美食體驗報告 3（2 組）\n第九週\t11/05\t期中考（分組唱一首馬來 / 印尼歌曲）\t\n第十週\t11/12\t這是什麼\t美食體驗報告 4（2 組）\n第十一週\t11/19\t你要點什麼\t美食體驗報告 5（2 組）\n第十二週\t11/26\t哪一個是你媽媽\t美食體驗報告 6（2 組）\n第十三週\t12/03\t你要買甚麼\t美食體驗報告 7（2 組）\n第十四週\t12/10\t你要搭甚麼車\t美食體驗報告 8（2 組）\n第十五週\t12/17\t期末分組口頭報告 （8-9 組）\t\n第十六週\t12/24\t期末分組口頭報告 （8-9 組）\t\n第十七週\t12/31\t馬來西亞美食體驗週\t\n第十八週\t01/07\t調課：校外參訪（11/9-10（六 - 日）馬來西亞日活動 @台博館南門館）",
    "scorePolicy": "缺席 3 次 (含請假) 不予學分\n1. 美食體驗分組口頭報告：25%\n2. 平時小考與出席率：25%\n3. 期中考（分組唱歌）：25%\n4. 期末分組口頭專題報告（分組）：25%    (加分題：參訪馬來西亞日活動)",
    "materials": "指定課本：（要上課的同學每人一本）*** 必須 ***\n《信不信由你：一週開口說馬來語》，王麗蘭著，台北：瑞蘭，2018。",
    "consultation": "leelan.wong@gmail.com",
    "課程對應SDGs指標": "SDG4：優質教育（Quality Education）SDG11：永續城市與社區（Sustainable Cities and Communities）SDG17：夥伴關係（Partnerships for the Goals）",
    "remarks": "",
    "foreignLanguageTextbooks": false
  }
]
