[
  {
    "name": "葉玉婷",
    "email": "yvette.yyeh@gmail.com",
    "latestUpdate": "2025-07-01 17:57:17",
    "objective": "本課程旨在教授學生如何運用創意編程和視覺化電腦圖形技術，將資料及音訊數據轉換為可視化之 2D 或 3D 視覺內容，藉以增進資料及音訊之閱聽體驗。課程進行中，學生將習得多種基於演算法之視覺表現方式，以滿足設計層面中富含躍動感、平衡感以及美感之體驗需求，活用創意編程與新媒體技術來創建更生動、更具有影響\n力的動靜態視聽影像。\nThis course aims to teach students how to utilize the knowledge from data science and computer graphics technology to represent data and audio into visualized 2D/3D representations, which gives rise to enhanced experiences of reading and listening. Students will learn a variety of programming skills to design visual representation based on algorithms to deliver dynamic, balanced and aesthetic experiences. With the help of creative coding and new media technology, more vivid and influential static and dynamic visual and audio experiences will be generated.",
    "schedule": "一、課程導論與案例導覽\n二、TouchDesigner\n三、設計與實作\n四、創作與應用\n五、專題實作 I\n六、成果展示\n七、p5.js\n八、資料結構與匯入\n九、音訊資料基礎分析\n十、聲音視覺化\n十一、資料視覺化\n十二、動態設計應用\n十三、課程期中驗收\n十四、視覺場景設計\n十五、演算法表現\n十六、專題實作 II\n十七、專題展示與成果發表\n十八、課程總結與回顧",
    "scorePolicy": "TouchDesigner 30%\np5.js 30%\n平時表現 40%",
    "materials": "使用自編教材",
    "consultation": "葉玉婷老師 yvette.yyeh@gmail.com",
    "課程對應SDGs指標": "SDG17：夥伴關係（Partnerships for the Goals）",
    "課程是否導入AI": "AI2：鼓勵學生使用生成式 AI 工具（Encourage students to use generative AI tools）",
    "remarks": "",
    "foreignLanguageTextbooks": false
  }
]
